py2pyd.py
module/__init__.py
module/fileConversion.py
module/single_py2pyd.py
gl_py2pyd-0.1.1.dist-info/METADATA
gl_py2pyd-0.1.1.dist-info/WHEEL
gl_py2pyd-0.1.1.dist-info/entry_points.txt
gl_py2pyd-0.1.1.dist-info/top_level.txt
gl_py2pyd-0.1.1.dist-info/RECORD
