Metadata-Version: 2.4
Name: gl-py2pyd
Version: 0.1.1
Summary: 将Python文件转换为pyd/so文件的工具
Home-page: https://github.com/youjunxiaji/py2pyd-arg
Author: gu lei
Author-email: youjunxiaji@gmail.com
Classifier: Programming Language :: Python :: 3
Classifier: License :: OSI Approved :: MIT License
Classifier: Operating System :: OS Independent
Requires-Python: >=3.6
Requires-Dist: cython
Requires-Dist: loguru
Dynamic: author
Dynamic: author-email
Dynamic: classifier
Dynamic: description
Dynamic: description-content-type
Dynamic: home-page
Dynamic: requires-dist
Dynamic: requires-python
Dynamic: summary
